ctfroute_k8s/__init__.py
ctfroute_k8s/watch.py
ctfroute_k8s/models/__init__.py
ctfroute_k8s/models/v1.py
ctfroute_k8s/utils/__init__.py
ctfroute_k8s/utils/async_helper.py
ctfroute_k8s/utils/sync_helper.py
ctfroute_k8s-0.4.0.dist-info/METADATA
ctfroute_k8s-0.4.0.dist-info/WHEEL
ctfroute_k8s-0.4.0.dist-info/RECORD
