Metadata-Version: 2.4
Name: ctfroute-k8s
Version: 0.4.0
Summary: Add your description here
Author-email: "no.shoes" <no.shoes@posteo.net>
License-Expression: MIT
Requires-Python: >=3.13
Requires-Dist: cloudcoil>=0.5.8
